MANIFEST.in
README.md
setup.py
g2p_kz.egg-info/PKG-INFO
g2p_kz.egg-info/SOURCES.txt
g2p_kz.egg-info/dependency_links.txt
g2p_kz.egg-info/requires.txt
g2p_kz.egg-info/top_level.txt
kzphoneme/__init__.py
kzphoneme/convert.py
kzphoneme/expand.py
kzphoneme/main.py
kzphoneme/normalize.py
kzphoneme/data/rightreading.kz