Metadata-Version: 2.1
Name: g2p-kz
Version: 0.0.4
Summary: Kazakh language grapheme to phoneme converter
Home-page: https://github.com/Ardaq/kz_g2p
Author: Ardaq
Author-email: ardager@163.com
License: UNKNOWN
Keywords: Kazakh,Phoneme
Platform: UNKNOWN
Classifier: Programming Language :: Python :: 3
Classifier: License :: OSI Approved :: MIT License
Requires-Python: >=3.6
